README.md
VERSION
src/opentelemetry/semconv/llm/__init__.py
opentelemetry_semconv_llm-0.0.1.dist-info/METADATA
opentelemetry_semconv_llm-0.0.1.dist-info/WHEEL
opentelemetry_semconv_llm-0.0.1.dist-info/RECORD
